pureauth_pysdk/__init__.py
pureauth_pysdk/docs/sdkmethods.ipynb
pureauth_pysdk/docs/sdkmethods_v2.ipynb
pureauth_pysdk/dto.py
pureauth_pysdk/errors.py
pureauth_pysdk/pureauth.py
pureauth_pysdk/sync/__init__.py
pureauth_pysdk/sync/errors.py
pureauth_pysdk/sync/sync.py
pureauth_pysdk/sync/v1/__init__.py
pureauth_pysdk/sync/v1/dto.py
pureauth_pysdk/sync/v1/employee.py
pureauth_pysdk/sync/v1/errors.py
pureauth_pysdk/sync/v1/organization.py
pureauth_pysdk/sync/v2/__init__.py
pureauth_pysdk/sync/v2/dto.py
pureauth_pysdk/sync/v2/employee.py
pureauth_pysdk/sync/v2/errors.py
pureauth_pysdk/sync/v2/organization.py
pureauth_pysdk/utils.py
pureauth_pysdk-2.1.2.dist-info/METADATA
pureauth_pysdk-2.1.2.dist-info/WHEEL
pureauth_pysdk-2.1.2.dist-info/RECORD
