Metadata-Version: 2.1
Name: pureauth-pysdk
Version: 2.1.2
Summary: pureauth-sdk contains all functions and classes to work with PureAUTH authentication platform
Author: PureID Labs
Author-email: hello@pureid.io
Requires-Python: >=3.8,<4.0
Classifier: Programming Language :: Python :: 3
Classifier: Programming Language :: Python :: 3.8
Classifier: Programming Language :: Python :: 3.9
Classifier: Programming Language :: Python :: 3.10
Classifier: Programming Language :: Python :: 3.11
Classifier: Programming Language :: Python :: 3.12
Requires-Dist: cryptography (>=42.0.5,<43.0.0)
Requires-Dist: ecdsa (>=0.18.0,<0.19.0)
Requires-Dist: requests (>=2.31.0,<3.0.0)
Requires-Dist: setuptools (>=69.1.1,<70.0.0)
